yupi/__init__.py
yupi/_checkers.py
yupi/_differentiation.py
yupi/exceptions.py
yupi/trajectory.py
yupi/units.py
yupi/vector.py
yupi/core/__init__.py
yupi/core/featurizers/__init__.py
yupi/core/featurizers/_acceleration_ftz.py
yupi/core/featurizers/_angle_ftz.py
yupi/core/featurizers/_kinetic_ftz.py
yupi/core/featurizers/_spatial_ftz.py
yupi/core/featurizers/_time_ftz.py
yupi/core/featurizers/_universal_ftz.py
yupi/core/featurizers/_velocity_ftz.py
yupi/core/featurizers/featurizer.py
yupi/core/serializers/__init__.py
yupi/core/serializers/csv_serializer.py
yupi/core/serializers/json_serializer.py
yupi/core/serializers/serializer.py
yupi/generators/__init__.py
yupi/generators/_generators.py
yupi/graphics/__init__.py
yupi/graphics/_stats_plots.py
yupi/graphics/_style.py
yupi/graphics/_trajs_plots.py
yupi/stats/__init__.py
yupi/stats/_stats.py
yupi/stats/kurtosis.py
yupi/stats/msd.py
yupi/stats/psd.py
yupi/stats/speed.py
yupi/stats/turning_angles.py
yupi/stats/vacf.py
yupi/tracking/__init__.py
yupi/tracking/algorithms.py
yupi/tracking/trackers.py
yupi/tracking/undistorters.py
yupi/transformations/__init__.py
yupi/transformations/_affine_estimator.py
yupi/transformations/_basics.py
yupi/transformations/_filters.py
yupi/transformations/_resamplers.py
yupi/transformations/_transformations.py
yupi-1.0.2.dist-info/licenses/LICENSE
yupi-1.0.2.dist-info/METADATA
yupi-1.0.2.dist-info/WHEEL
yupi-1.0.2.dist-info/top_level.txt
yupi-1.0.2.dist-info/RECORD
