Metadata-Version: 2.4
Name: yupi
Version: 1.0.2
Summary: A package for tracking and analysing objects trajectories
Author-email: Gustavo Viera-López <gvieralopez@gmail.com>, Alfredo Reyes <areyes@fisica.uh.cu>, Jorge Morgado <jorge.morgadov@gmail.com>, Ernesto Altshuler <ealtshuler@fisica.uh.cu>
License-Expression: MIT
Project-URL: Repository, https://github.com/yupidevs/yupi
Project-URL: Documentation, https://yupi.readthedocs.io
Keywords: trajectory,analysis,tracking
Requires-Python: >=3.10
License-File: LICENSE
Requires-Dist: opencv-python>=4.4.0
Requires-Dist: numpy>=1.16.5
Requires-Dist: nudged>=0.3.1
Requires-Dist: matplotlib>=3.2.0
Dynamic: license-file
